pycrtbp/__init__.py
pycrtbp/particles.py
pycrtbp/periodicorbits.py
pycrtbp/system.py
pycrtbp/version.py
pycrtbp-0.1.6.dist-info/LICENSE
pycrtbp-0.1.6.dist-info/METADATA
pycrtbp-0.1.6.dist-info/WHEEL
pycrtbp-0.1.6.dist-info/entry_points.txt
pycrtbp-0.1.6.dist-info/top_level.txt
pycrtbp-0.1.6.dist-info/RECORD
