Metadata-Version: 2.1
Name: pycrtbp
Version: 0.1.6
Summary: CRTBP Integrator and Tools
Home-page: https://pypi.org/project/pycrtbp
Author: Diego A. Acosta & Jorge I. Zuluaga
Author-email: diego.acostab@udea.edu.co
License: MIT
Keywords: astrodynamics
Classifier: Programming Language :: Python :: 3
Classifier: License :: OSI Approved :: MIT License
Classifier: Operating System :: OS Independent
License-File: LICENSE
Requires-Dist: scipy
Requires-Dist: pytest
